InterfaceBuilderKit/__init__.py
InterfaceBuilderKit/_metadata.py
pyobjc_framework_InterfaceBuilderKit-7.3.dist-info/LICENSE.txt
pyobjc_framework_InterfaceBuilderKit-7.3.dist-info/METADATA
pyobjc_framework_InterfaceBuilderKit-7.3.dist-info/WHEEL
pyobjc_framework_InterfaceBuilderKit-7.3.dist-info/top_level.txt
pyobjc_framework_InterfaceBuilderKit-7.3.dist-info/RECORD
