Metadata-Version: 2.1
Name: pyobjc-framework-InterfaceBuilderKit
Version: 7.3
Summary: Wrappers for the framework InterfaceBuilderKit on macOS
Home-page: https://github.com/ronaldoussoren/pyobjc
Author: Ronald Oussoren
Author-email: pyobjc-dev@lists.sourceforge.net
License: MIT License
Keywords: PyObjC,InterfaceBuilderKit
Platform: MacOS X (>=10.5, <=10.6)
Classifier: Development Status :: 5 - Production/Stable
Classifier: Environment :: Console
Classifier: Environment :: MacOS X :: Cocoa
Classifier: Intended Audience :: Developers
Classifier: License :: OSI Approved :: MIT License
Classifier: Natural Language :: English
Classifier: Operating System :: MacOS :: MacOS X
Classifier: Programming Language :: Python
Classifier: Programming Language :: Python :: 3
Classifier: Programming Language :: Python :: 3.6
Classifier: Programming Language :: Python :: 3.7
Classifier: Programming Language :: Python :: 3.8
Classifier: Programming Language :: Python :: 3.9
Classifier: Programming Language :: Python :: Implementation :: CPython
Classifier: Programming Language :: Objective C
Classifier: Topic :: Software Development :: Libraries :: Python Modules
Classifier: Topic :: Software Development :: User Interfaces
Requires-Python: >=3.6
License-File: LICENSE.txt
Requires-Dist: pyobjc-core (>=7.3)
Requires-Dist: pyobjc-framework-Cocoa (>=7.3)
